promptons/__init__.py
promptons/pyproject.toml
promptons-0.1.0.dist-info/LICENSE
promptons-0.1.0.dist-info/METADATA
promptons-0.1.0.dist-info/WHEEL
promptons-0.1.0.dist-info/RECORD
